.github/tre-light.png
tile_renderer/__about__.py
tile_renderer/__init__.py
tile_renderer/__main__.py
tile_renderer/_logger.py
tile_renderer/colour.py
tile_renderer/component_to_svg.py
tile_renderer/coord.py
tile_renderer/pla1to2.py
tile_renderer/pla2.py
tile_renderer/py.typed
tile_renderer/render_svg.py
tile_renderer/render_tiles.py
tile_renderer/cli/__init__.py
tile_renderer/skin/__init__.py
tile_renderer/skin/default_licences.md
tile_renderer/skin/generate_default.py
tile_renderer/skin/default_icons/baseball-bat-ball.svg
tile_renderer/skin/default_icons/bed.svg
tile_renderer/skin/default_icons/bicycle.svg
tile_renderer/skin/default_icons/book.svg
tile_renderer/skin/default_icons/building-columns.svg
tile_renderer/skin/default_icons/camera.svg
tile_renderer/skin/default_icons/cart-shopping.svg
tile_renderer/skin/default_icons/droplet.svg
tile_renderer/skin/default_icons/dumbbell.svg
tile_renderer/skin/default_icons/film.svg
tile_renderer/skin/default_icons/gamepad.svg
tile_renderer/skin/default_icons/gas-pump.svg
tile_renderer/skin/default_icons/house-chimney-medical.svg
tile_renderer/skin/default_icons/people-roof.svg
tile_renderer/skin/default_icons/place-of-worship.svg
tile_renderer/skin/default_icons/plane.svg
tile_renderer/skin/default_icons/right-from-bracket.svg
tile_renderer/skin/default_icons/square-parking.svg
tile_renderer/skin/default_icons/store.svg
tile_renderer/skin/default_icons/traffic-light.svg
tile_renderer/skin/default_icons/train.svg
tile_renderer/skin/default_icons/utensils.svg
tile_renderer-5.0.8.dist-info/METADATA
tile_renderer-5.0.8.dist-info/WHEEL
tile_renderer-5.0.8.dist-info/entry_points.txt
tile_renderer-5.0.8.dist-info/licenses/LICENSE
tile_renderer-5.0.8.dist-info/RECORD
