Metadata-Version: 2.4
Name: tile-renderer
Version: 5.0.8
Summary: Street map renderer built for the Minecart Rapid Transit City Map (https://mrt-map.github.io/map)
Project-URL: Documentation, https://mrt-map.github.io/tile-renderer
Project-URL: Issues, https://github.com/MRT-Map/tile-renderer/issues
Project-URL: Source, https://github.com/MRT-Map/tile-renderer
Project-URL: Changelog, https://github.com/MRT-Map/tile-renderer/blob/main/CHANGELOG.md
Author-email: 7d <61975820+iiiii7d@users.noreply.github.com>, Minecart Rapid Transit Mapping Services <mappingmrt@gmail.com>
License:                     GNU GENERAL PUBLIC LICENSE
License-File: LICENSE
Keywords: map,mapping,minecart rapid transit,mrt mapping services,renderer,tile-renderer,tiles
Classifier: Development Status :: 5 - Production/Stable
Classifier: Intended Audience :: Developers
Classifier: License :: OSI Approved :: GNU General Public License v3 (GPLv3)
Classifier: Natural Language :: English
Classifier: Programming Language :: Python :: 3.12
Classifier: Programming Language :: Python :: Implementation :: CPython
Requires-Python: >=3.12
Requires-Dist: click~=8.1
Requires-Dist: msgspec~=0.19
Requires-Dist: niquests~=3.14
Requires-Dist: rich~=14.0
Requires-Dist: shapely~=2.0
Requires-Dist: svg-py~=1.6
